README.txt
setup.py
svn_ignore.txt
docs/AUTHORS.txt
docs/CHANGES.txt
docs/INSTALL.txt
docs/LICENSE.GPL
docs/LICENSE.txt
p4a/__init__.py
p4a.ploneimage.egg-info/PKG-INFO
p4a.ploneimage.egg-info/SOURCES.txt
p4a.ploneimage.egg-info/dependency_links.txt
p4a.ploneimage.egg-info/entry_points.txt
p4a.ploneimage.egg-info/namespace_packages.txt
p4a.ploneimage.egg-info/not-zip-safe
p4a.ploneimage.egg-info/requires.txt
p4a.ploneimage.egg-info/top_level.txt
p4a/ploneimage/__init__.py
p4a/ploneimage/atct.py
p4a/ploneimage/browser.txt
p4a/ploneimage/configure.zcml
p4a/ploneimage/content.py
p4a/ploneimage/geoimage.py
p4a/ploneimage/install.txt
p4a/ploneimage/media.py
p4a/ploneimage/plone-image-impl.txt
p4a/ploneimage/plone-image.txt
p4a/ploneimage/profiles.zcml
p4a/ploneimage/sitesetup.py
p4a/ploneimage/syndication.py
p4a/ploneimage/syndication.txt
p4a/ploneimage/syndication.zcml
p4a/ploneimage/testing.py
p4a/ploneimage/tests.py
p4a/ploneimage/atphoto/__init__.py
p4a/ploneimage/atphoto/ataudiotests.py
p4a/ploneimage/atphoto/browser.py
p4a/ploneimage/atphoto/configure.zcml
p4a/ploneimage/atphoto/interfaces.py
p4a/ploneimage/atphoto/migrate-ataudio-configlet.pt
p4a/ploneimage/atphoto/migration.py
p4a/ploneimage/atphoto/migration.txt
p4a/ploneimage/profiles/default/p4a.ploneimage_various.txt