Metadata-Version: 1.0
Name: p4a.ploneimage
Version: 0.2
Summary: UNKNOWN
Home-page: http://svn.plone.org/svn/plone/plone.example
Author: Rocky Burt
Author-email: rocky@serverzen.com
License: GPL
Platform: UNKNOWN
